sbmp/__init__.py
sbmp/sbmp.py
sbmp-5.0.12.dist-info/LICENSE
sbmp-5.0.12.dist-info/METADATA
sbmp-5.0.12.dist-info/WHEEL
sbmp-5.0.12.dist-info/top_level.txt
sbmp-5.0.12.dist-info/RECORD
