Metadata-Version: 2.1
Name: sbmp
Version: 5.0.12
Summary: SBMP
Home-page: 
Author: Jainam Barbhaya
Author-email: jainambarbhaya1509@gmail.com
License: MIT
Keywords: sbmp
Classifier: Development Status :: 5 - Production/Stable
Classifier: Intended Audience :: Education
Classifier: Operating System :: Microsoft :: Windows :: Windows 10
Classifier: License :: OSI Approved :: MIT License
Classifier: Programming Language :: Python :: 3
License-File: LICENSE
